wordtriepy/__init__.py
wordtriepy/wordtriepy.py
wordtriepy/assets/words_de.pkl
wordtriepy/assets/words_en.pkl
wordtriepy/assets/words_es.pkl
wordtriepy/assets/words_fr.pkl
wordtriepy/assets/words_pt.pkl
wordtriepy-0.0.3.dist-info/LICENSE
wordtriepy-0.0.3.dist-info/METADATA
wordtriepy-0.0.3.dist-info/WHEEL
wordtriepy-0.0.3.dist-info/top_level.txt
wordtriepy-0.0.3.dist-info/RECORD
