Metadata-Version: 2.1
Name: wordtriepy
Version: 0.0.3
Summary: A trie filled with words from several languages (English - en, German - de , French - fr, Spanish - es, Portuguese - pt)
Home-page: https://github.com/christian-vorhemus/wordtrie
Author: Christian Vorhemus
Author-email: 
Project-URL: Bug Tracker, https://github.com/christian-vorhemus/wordtrie/issues
Classifier: Programming Language :: Python :: 3
Classifier: License :: OSI Approved :: MIT License
Classifier: Operating System :: OS Independent
Requires-Python: >=3.5
License-File: LICENSE
